package/__init__.py
package/package1.py
package/package2.py
star1000_test2-1.0.dist-info/METADATA
star1000_test2-1.0.dist-info/WHEEL
star1000_test2-1.0.dist-info/top_level.txt
star1000_test2-1.0.dist-info/RECORD
