Metadata-Version: 2.1
Name: star1000-test2
Version: 1.0
Summary: Python test
Home-page: UNKNOWN
Author: CheonSunggil
Author-email: chkrdp@gmail.com
License: UNKNOWN
Platform: UNKNOWN
Requires-Python: >=3
